fastapi_spa_kit/__init__.py
fastapi_spa_kit-0.0.4.dist-info/LICENSE.txt
fastapi_spa_kit-0.0.4.dist-info/METADATA
fastapi_spa_kit-0.0.4.dist-info/WHEEL
fastapi_spa_kit-0.0.4.dist-info/top_level.txt
fastapi_spa_kit-0.0.4.dist-info/RECORD
