Metadata-Version: 2.1
Name: fastapi-spa-kit
Version: 0.0.4
Summary: Kit for developing SPA with FastAPI.
Home-page: https://github.com/swimmwatch/fastapi-spa-kit
Author: Dmitry Vasiliev
License: UNKNOWN
Project-URL: Bug Tracker, https://github.com/swimmwatch/fastapi-spa-kit/issues
Platform: UNKNOWN
Classifier: Programming Language :: Python :: 3
Classifier: License :: OSI Approved :: MIT License
Classifier: Operating System :: OS Independent
